setup.py
zoomlet/__init__.py
zoomlet/zoomlet.py
zoomlet.egg-info/PKG-INFO
zoomlet.egg-info/SOURCES.txt
zoomlet.egg-info/dependency_links.txt
zoomlet.egg-info/requires.txt
zoomlet.egg-info/top_level.txt