Metadata-Version: 2.1
Name: zoomlet
Version: 0.1
Summary: Box plot visualization library
Author: Vinil
Author-email: vinilharsh123@gmail.com
Classifier: Programming Language :: Python :: 3
Classifier: License :: OSI Approved :: MIT License
Classifier: Operating System :: OS Independent
